LICENSE
MANIFEST.in
README.rst
setup.py
LICENSES/GLMNET_LICENSE
LICENSES/SCIKIT_LEARN_LICENSE
glmnet2/__init__.py
glmnet2/_glmnet2.py
glmnet2/doc.py
glmnet2/errors.py
glmnet2/linear.py
glmnet2/logistic.py
glmnet2/scorer.py
glmnet2/util.py
glmnet2.egg-info/PKG-INFO
glmnet2.egg-info/SOURCES.txt
glmnet2.egg-info/dependency_links.txt
glmnet2.egg-info/requires.txt
glmnet2.egg-info/top_level.txt
glmnet2/src/glmnet2/glmnet5.f90
glmnet2/tests/__init__.py
glmnet2/tests/test_errors.py
glmnet2/tests/test_linear.py
glmnet2/tests/test_logistic.py
glmnet2/tests/test_pandas.py
glmnet2/tests/test_util.py
glmnet2/tests/util.py